salkikal_package1/salkikal_module1.py
salkikal_package1-0.1.0.dist-info/METADATA
salkikal_package1-0.1.0.dist-info/WHEEL
salkikal_package1-0.1.0.dist-info/top_level.txt
salkikal_package1-0.1.0.dist-info/RECORD
