Metadata-Version: 2.1
Name: salkikal-package1
Version: 0.1.0
Summary: A package with a Base class
Author: Salome Kikalishvili
Author-email: salomekikalishvili2000@gmail.com
